LICENCE.txt
MANIFEST.in
README.rst
setup.cfg
setup.py
djangocms_inspector/__init__.py
djangocms_inspector/apps.py
djangocms_inspector/exceptions.py
djangocms_inspector/settings.py
djangocms_inspector/urls.py
djangocms_inspector.egg-info/PKG-INFO
djangocms_inspector.egg-info/SOURCES.txt
djangocms_inspector.egg-info/dependency_links.txt
djangocms_inspector.egg-info/requires.txt
djangocms_inspector.egg-info/top_level.txt
djangocms_inspector.egg-info/zip-safe
djangocms_inspector/factories/__init__.py
djangocms_inspector/templates/djangocms_inspector/plugins_report.html
djangocms_inspector/templatetags/__init__.py
djangocms_inspector/templatetags/djangocms_inspector.py